iblox/__init__.py
iblox-2.0.0.dist-info/METADATA
iblox-2.0.0.dist-info/WHEEL
iblox-2.0.0.dist-info/licenses/LICENSE
iblox-2.0.0.dist-info/licenses/LICENSE.lesser
iblox-2.0.0.dist-info/RECORD
