Metadata-Version: 2.4
Name: iblox
Version: 2.0.0
Summary: Infoblox WAPI Module
Project-URL: Homepage, http://iblox.readthedocs.io/
Project-URL: Repository, https://bitbucket.org/isaiah1112/infoblox
Author-email: Jesse Almanrode <jesse@almanrode.com>
License-Expression: LGPL-3.0-or-later
License-File: LICENSE
License-File: LICENSE.lesser
Classifier: Development Status :: 5 - Production/Stable
Classifier: Intended Audience :: Developers
Classifier: License :: OSI Approved :: GNU Lesser General Public License v3 or later (LGPLv3+)
Classifier: Programming Language :: Python
Classifier: Programming Language :: Python :: 3.9
Classifier: Programming Language :: Python :: 3.10
Classifier: Programming Language :: Python :: 3.11
Classifier: Programming Language :: Python :: 3.12
Classifier: Programming Language :: Python :: 3.13
Classifier: Topic :: Software Development
Classifier: Topic :: Software Development :: Libraries
Classifier: Topic :: Software Development :: Libraries :: Python Modules
Requires-Python: <4.0,>3.9
Requires-Dist: requests>=2.25.1
